{"box_data": [{"position": {"minX": 2, "maxX": 40, "minY": 72, "maxY": 128}, "class_id": 0, "box_caption": "car", "domain": "pixel"}, {"position": {"minX": 23, "maxX": 41, "minY": 70, "maxY": 92}, "class_id": 0, "box_caption": "car", "domain": "pixel"}, {"position": {"minX": 59, "maxX": 82, "minY": 57, "maxY": 91}, "class_id": 2, "box_caption": "bus", "domain": "pixel"}, {"position": {"minX": 58, "maxX": 105, "minY": 82, "maxY": 128}, "class_id": 0, "box_caption": "car", "domain": "pixel"}, {"position": {"minX": 120, "maxX": 234, "minY": 95, "maxY": 128}, "class_id": 0, "box_caption": "car", "domain": "pixel"}, {"position": {"minX": 211, "maxX": 215, "minY": 68, "maxY": 82}, "class_id": 6, "box_caption": "person", "domain": "pixel"}, {"position": {"minX": 369, "maxX": 445, "minY": 94, "maxY": 128}, "class_id": 0, "box_caption": "car", "domain": "pixel"}, {"position": {"minX": 441, "maxX": 484, "minY": 72, "maxY": 128}, "class_id": 0, "box_caption": "car", "domain": "pixel"}, {"position": {"minX": 493, "maxX": 532, "minY": 83, "maxY": 128}, "class_id": 0, "box_caption": "car", "domain": "pixel"}, {"position": {"minX": 563, "maxX": 570, "minY": 71, "maxY": 103}, "class_id": 7, "box_caption": "rider", "domain": "pixel"}, {"position": {"minX": 561, "maxX": 575, "minY": 85, "maxY": 101}, "class_id": 4, "box_caption": "bicycle", "domain": "pixel"}, {"position": {"minX": 552, "maxX": 558, "minY": 72, "maxY": 93}, "class_id": 7, "box_caption": "rider", "domain": "pixel"}, {"position": {"minX": 700, "maxX": 703, "minY": 75, "maxY": 86}, "class_id": 6, "box_caption": "person", "domain": "pixel"}], "class_labels": {"0": "car", "1": "truck", "2": "bus", "3": "motorcycle", "4": "bicycle", "5": "scooter", "6": "person", "7": "rider"}}